<?xml version="1.0" encoding="utf-8"?>
<Level1>
  <room1>
    <type>
      <blocks num="18">
        <B>
          <loc>
            <x>100</x>
            <y>100</y>
          </loc>
          <B_texture>floor</B_texture>
        </B>
        <B>
          <loc>
            <x>0</x>
            <y>0</y>
          </loc>
          <B_texture>leftwall</B_texture>
        </B>
        <B>
          <loc>
            <x>100</x>
            <y>0</y>
          </loc>
          <B_texture>topwall</B_texture>
        </B>
        <B>
          <loc>
            <x>700</x>
            <y>0</y>
          </loc>
          <B_texture>rightwall</B_texture>
        </B>
        <B>
          <loc>
            <x>100</x>
            <y>450</y>
          </loc>
          <B_texture>bottomwall</B_texture>
        </B>
        <B>
          <loc>
            <x>350</x>
            <y>0</y>
          </loc>
          <B_texture>topwall11</B_texture>
        </B>
        <B>
          <loc>
            <x>700</x>
            <y>225</y>
          </loc>
          <B_texture>rightgate</B_texture>
        </B>
        <B>
          <loc>
            <x>350</x>
            <y>450</y>
          </loc>
          <B_texture>bottomwall11</B_texture>
        </B>
        <B>
          <loc>
            <x>0</x>
            <y>225</y>
          </loc>
          <B_texture>leftwall11</B_texture>
        </B>
        <B>
          <loc>
            <x>300</x>
            <y>250</y>
          </loc>
          <B_texture>block</B_texture>
        </B>
        <B>
          <loc>
            <x>350</x>
            <y>200</y>
          </loc>
          <B_texture>block</B_texture>
        </B>
        <B>
          <loc>
            <x>400</x>
            <y>150</y>
          </loc>
          <B_texture>block</B_texture>
        </B>
        <B>
          <loc>
            <x>450</x>
            <y>200</y>
          </loc>
          <B_texture>block</B_texture>
        </B>
        <B>
          <loc>
            <x>500</x>
            <y>250</y>
          </loc>
          <B_texture>block</B_texture>
        </B>
        <B>
          <loc>
            <x>450</x>
            <y>300</y>
          </loc>
          <B_texture>block</B_texture>
        </B>
        <B>
          <loc>
            <x>400</x>
            <y>350</y>
          </loc>
          <B_texture>block</B_texture>
        </B>
        <B>
          <loc>
            <x>350</x>
            <y>300</y>
          </loc>
          <B_texture>block</B_texture>
        </B>
        <B>
          <loc>
            <x>400</x>
            <y>250</y>
          </loc>
          <B_texture>stairs</B_texture>
        </B>
      </blocks>
      <items num="0" />
		<enemies num="4">
			<E move="true">
				<loc>
					<x>100</x>
					<y>100</y>
				</loc>
				<dir>3</dir>
				<E_texture>
					<up>bladetrap</up>
					<down>bladetrap</down>
					<right>bladetrap</right>
					<left>bladetrap</left>
				</E_texture>
				<projectile fire="false"/>
				<routes>
					<R>
						<loc>
							<x>100</x>
							<y>400</y>
						</loc>
						<dir>2</dir>
					</R>
				</routes>
				<timer/>
			</E>
			<E move="true">
				<loc>
					<x>100</x>
					<y>400</y>
				</loc>
				<dir>2</dir>
				<E_texture>
					<up>bladetrap</up>
					<down>bladetrap</down>
					<right>bladetrap</right>
					<left>bladetrap</left>
				</E_texture>
				<projectile fire="false"/>
				<routes>
					<R>
						<loc>
							<x>100</x>
							<y>100</y>
						</loc>
						<dir>3</dir>
					</R>
				</routes>
				<timer/>
			</E>
			<E move="true">
				<loc>
					<x>650</x>
					<y>100</y>
				</loc>
				<dir>3</dir>
				<E_texture>
					<up>bladetrap</up>
					<down>bladetrap</down>
					<right>bladetrap</right>
					<left>bladetrap</left>
				</E_texture>
				<projectile fire="false"/>
				<routes>
					<R>
						<loc>
							<x>650</x>
							<y>400</y>
						</loc>
						<dir>2</dir>
					</R>
				</routes>
				<timer/>
			</E>
			<E move="true">
				<loc>
					<x>650</x>
					<y>400</y>
				</loc>
				<dir>2</dir>
				<E_texture>
					<up>bladetrap</up>
					<down>bladetrap</down>
					<right>bladetrap</right>
					<left>bladetrap</left>
				</E_texture>
				<projectile fire="false"/>
				<routes>
					<R>
						<loc>
							<x>650</x>
							<y>100</y>
						</loc>
						<dir>3</dir>
					</R>
				</routes>
				<timer/>
			</E>
		</enemies>
    </type>
  </room1>
  <room2>
    <type>
      <blocks num="17">
        <B>
          <loc>
            <x>100</x>
            <y>100</y>
          </loc>
          <B_texture>floor</B_texture>
        </B>
        <B>
          <loc>
            <x>0</x>
            <y>0</y>
          </loc>
          <B_texture>leftwall</B_texture>
        </B>
        <B>
          <loc>
            <x>100</x>
            <y>0</y>
          </loc>
          <B_texture>topwall</B_texture>
        </B>
        <B>
          <loc>
            <x>700</x>
            <y>0</y>
          </loc>
          <B_texture>rightwall</B_texture>
        </B>
        <B>
          <loc>
            <x>100</x>
            <y>450</y>
          </loc>
          <B_texture>bottomwall</B_texture>
        </B>
        <B>
          <loc>
            <x>0</x>
            <y>225</y>
          </loc>
          <B_texture>leftgate</B_texture>
        </B>
        <B>
          <loc>
            <x>350</x>
            <y>0</y>
          </loc>
          <B_texture>topwall11</B_texture>
        </B>
        <B>
          <loc>
            <x>700</x>
            <y>225</y>
          </loc>
          <B_texture>rightwall11</B_texture>
        </B>
        <B>
          <loc>
            <x>350</x>
            <y>450</y>
          </loc>
          <B_texture>bottomgate</B_texture>
        </B>
        <B>
          <loc>
            <x>150</x>
            <y>150</y>
          </loc>
          <B_texture>water13</B_texture>
        </B>
        <B>
          <loc>
            <x>150</x>
            <y>200</y>
          </loc>
          <B_texture>water31</B_texture>
        </B>
        <B>
          <loc>
            <x>150</x>
            <y>350</y>
          </loc>
          <B_texture>water13</B_texture>
        </B>
        <B>
          <loc>
            <x>250</x>
            <y>250</y>
          </loc>
          <B_texture>water13</B_texture>
        </B>
        <B>
          <loc>
            <x>400</x>
            <y>250</y>
          </loc>
          <B_texture>water13</B_texture>
        </B>
        <B>
          <loc>
            <x>500</x>
            <y>150</y>
          </loc>
          <B_texture>water13</B_texture>
        </B>
        <B>
          <loc>
            <x>600</x>
            <y>200</y>
          </loc>
          <B_texture>water31</B_texture>
        </B>
        <B>
          <loc>
            <x>500</x>
            <y>350</y>
          </loc>
          <B_texture>water13</B_texture>
        </B>
      </blocks>
      <items num="1">
		  <I>
			  <loc>
				  <x>400</x>
				  <y>153</y>
			  </loc>
			  <I_texture>key</I_texture>
		  </I>
	   </items>
		<enemies num="3">
			<E move="true">
				<loc>
					<x>450</x>
					<y>90</y>
				</loc>
				<dir>1</dir>
				<E_texture>
					<up>redGoriyaBack</up>
					<down>redGoriyaFront</down>
					<right>redGoriyaRight</right>
					<left>redGoriyaLeft</left>
				</E_texture>
				<projectile fire="false"/>
				<routes>
					<R>
						<loc>
							<x>300</x>
							<y>90</y>
						</loc>
						<dir>3</dir>
					</R>
					<R>
						<loc>
							<x>300</x>
							<y>190</y>
						</loc>
						<dir>0</dir>
					</R>
					<R>
						<loc>
							<x>450</x>
							<y>190</y>
						</loc>
						<dir>2</dir>
					</R>
				</routes>
				<timer/>
			</E>
			<E move="true">
				<loc>
					<x>450</x>
					<y>190</y>
				</loc>
				<dir>1</dir>
				<E_texture>
					<up>redGoriyaBack</up>
					<down>redGoriyaFront</down>
					<right>redGoriyaRight</right>
					<left>redGoriyaLeft</left>
				</E_texture>
				<projectile fire="false"/>
				<routes>
					<R>
						<loc>
							<x>200</x>
							<y>190</y>
						</loc>
						<dir>3</dir>
					</R>
					<R>
						<loc>
							<x>200</x>
							<y>290</y>
						</loc>
						<dir>0</dir>
					</R>
					<R>
						<loc>
							<x>550</x>
							<y>290</y>
						</loc>
						<dir>2</dir>
					</R>
					<R>
						<loc>
							<x>550</x>
							<y>190</y>
						</loc>
						<dir>1</dir>
					</R>
				</routes>
				<timer/>
			</E>
			<E move="true">
				<loc>
					<x>500</x>
					<y>290</y>
				</loc>
				<dir>0</dir>
				<E_texture>
					<up>redGoriyaBack</up>
					<down>redGoriyaFront</down>
					<right>redGoriyaRight</right>
					<left>redGoriyaLeft</left>
				</E_texture>
				<projectile fire="false"/>
				<routes>
					<R>
						<loc>
							<x>550</x>
							<y>290</y>
						</loc>
						<dir>2</dir>
					</R>
					<R>
						<loc>
							<x>550</x>
							<y>190</y>
						</loc>
						<dir>1</dir>
					</R>
					<R>
						<loc>
							<x>400</x>
							<y>190</y>
						</loc>
						<dir>0</dir>
					</R>
					<R>
						<loc>
							<x>550</x>
							<y>190</y>
						</loc>
						<dir>3</dir>
					</R>
					<R>
						<loc>
							<x>550</x>
							<y>290</y>
						</loc>
						<dir>1</dir>
					</R>
				</routes>
				<timer/>
			</E>
		</enemies>
    </type>
  </room2>
  <room3>
    <type>
      <blocks num="25">
        <B>
          <loc>
            <x>100</x>
            <y>100</y>
          </loc>
          <B_texture>floor</B_texture>
        </B>
        <B>
          <loc>
            <x>0</x>
            <y>0</y>
          </loc>
          <B_texture>leftwall</B_texture>
        </B>
        <B>
          <loc>
            <x>100</x>
            <y>0</y>
          </loc>
          <B_texture>topwall</B_texture>
        </B>
        <B>
          <loc>
            <x>700</x>
            <y>0</y>
          </loc>
          <B_texture>rightwall</B_texture>
        </B>
        <B>
          <loc>
            <x>100</x>
            <y>450</y>
          </loc>
          <B_texture>bottomwall</B_texture>
        </B>
        <B>
          <loc>
            <x>0</x>
            <y>225</y>
          </loc>
          <B_texture>leftwall11</B_texture>
        </B>
        <B>
          <loc>
            <x>350</x>
            <y>0</y>
          </loc>
          <B_texture>topgate</B_texture>
        </B>
        <B>
          <loc>
            <x>700</x>
            <y>225</y>
          </loc>
          <B_texture>rightwall11</B_texture>
        </B>
        <B>
          <loc>
            <x>350</x>
            <y>450</y>
          </loc>
          <B_texture>bottomgate</B_texture>
        </B>
        <B>
          <loc>
            <x>100</x>
            <y>100</y>
          </loc>
          <B_texture>water31</B_texture>
        </B>
        <B>
          <loc>
            <x>150</x>
            <y>100</y>
          </loc>
          <B_texture>water13</B_texture>
        </B>
        <B>
          <loc>
            <x>300</x>
            <y>100</y>
          </loc>
          <B_texture>water51</B_texture>
        </B>
        <B>
          <loc>
            <x>350</x>
            <y>300</y>
          </loc>
          <B_texture>water11</B_texture>
        </B>
        <B>
          <loc>
            <x>100</x>
            <y>300</y>
          </loc>
          <B_texture>water31</B_texture>
        </B>
        <B>
          <loc>
            <x>150</x>
            <y>400</y>
          </loc>
          <B_texture>water11</B_texture>
        </B>
        <B>
          <loc>
            <x>200</x>
            <y>200</y>
          </loc>
          <B_texture>water51</B_texture>
        </B>
        <B>
          <loc>
            <x>250</x>
            <y>400</y>
          </loc>
          <B_texture>water12</B_texture>
        </B>
        <B>
          <loc>
            <x>450</x>
            <y>100</y>
          </loc>
          <B_texture>water12</B_texture>
        </B>
        <B>
          <loc>
            <x>550</x>
            <y>100</y>
          </loc>
          <B_texture>water51</B_texture>
        </B>
        <B>
          <loc>
            <x>600</x>
            <y>100</y>
          </loc>
          <B_texture>water11</B_texture>
        </B>
        <B>
          <loc>
            <x>650</x>
            <y>100</y>
          </loc>
          <B_texture>water31</B_texture>
        </B>
        <B>
          <loc>
            <x>400</x>
            <y>200</y>
          </loc>
          <B_texture>water11</B_texture>
        </B>
        <B>
          <loc>
            <x>450</x>
            <y>200</y>
          </loc>
          <B_texture>water51</B_texture>
        </B>
        <B>
          <loc>
            <x>500</x>
            <y>400</y>
          </loc>
          <B_texture>water13</B_texture>
        </B>
        <B>
          <loc>
            <x>650</x>
            <y>300</y>
          </loc>
          <B_texture>water31</B_texture>
        </B>
      </blocks>
		<items num="1">
			<I>
				<loc>
					<x>600</x>
					<y>144</y>
				</loc>
				<I_texture>key</I_texture>
			</I>
		</items>
		<enemies num="3">
			<E move="true">
				<loc>
					<x>152</x>
					<y>138</y>
				</loc>
				<dir>0</dir>
				<E_texture>
					<up>stalfos</up>
					<down>stalfos</down>
					<right>stalfos</right>
					<left>stalfos</left>
				</E_texture>
				<projectile fire="false"/>
				<routes>
					<R>
						<loc>
							<x>245</x>
							<y>138</y>
						</loc>
						<dir>3</dir>
					</R>
					<R>
						<loc>
							<x>245</x>
							<y>335</y>
						</loc>
						<dir>0</dir>
					</R>
					<R>
						<loc>
							<x>395</x>
							<y>335</y>
						</loc>
						<dir>1</dir>
					</R>
					<R>
						<loc>
							<x>245</x>
							<y>335</y>
						</loc>
						<dir>2</dir>
					</R>
					<R>
						<loc>
							<x>245</x>
							<y>138</y>
						</loc>
						<dir>1</dir>
					</R>
				</routes>
				<timer/>
			</E>
			<E move="true">
				<loc>
					<x>598</x>
					<y>173</y>
				</loc>
				<dir>3</dir>
				<E_texture>
					<up>stalfos</up>
					<down>stalfos</down>
					<right>stalfos</right>
					<left>stalfos</left>
				</E_texture>
				<projectile fire="false"/>
				<routes>
					<R>
						<loc>
							<x>598</x>
							<y>336</y>
						</loc>
						<dir>2</dir>
					</R>
				</routes>
				<timer/>
			</E>
			<E move="true">
				<loc>
					<x>348</x>
					<y>136</y>
				</loc>
				<dir>0</dir>
				<E_texture>
					<up>stalfos</up>
					<down>stalfos</down>
					<right>stalfos</right>
					<left>stalfos</left>
				</E_texture>
				<projectile fire="false"/>
				<routes>
					<R>
						<loc>
							<x>497</x>
							<y>136</y>
						</loc>
						<dir>3</dir>
					</R>
					<R>
						<loc>
							<x>497</x>
							<y>336</y>
						</loc>
						<dir>2</dir>
					</R>
					<R>
						<loc>
							<x>497</x>
							<y>136</y>
						</loc>
						<dir>1</dir>
					</R>
				</routes>
				<timer/>
			</E>
		</enemies>
    </type>
  </room3>
  <room4>
    <type>
      <blocks num="15">
        <B>
          <loc>
            <x>100</x>
            <y>100</y>
          </loc>
          <B_texture>floor</B_texture>
        </B>
        <B>
          <loc>
            <x>0</x>
            <y>0</y>
          </loc>
          <B_texture>leftwall</B_texture>
        </B>
        <B>
          <loc>
            <x>100</x>
            <y>0</y>
          </loc>
          <B_texture>topwall</B_texture>
        </B>
        <B>
          <loc>
            <x>700</x>
            <y>0</y>
          </loc>
          <B_texture>rightwall</B_texture>
        </B>
        <B>
          <loc>
            <x>100</x>
            <y>450</y>
          </loc>
          <B_texture>bottomwall</B_texture>
        </B>
        <B>
          <loc>
            <x>0</x>
            <y>225</y>
          </loc>
          <B_texture>leftwall11</B_texture>
        </B>
        <B>
          <loc>
            <x>350</x>
            <y>0</y>
          </loc>
          <B_texture>topwall11</B_texture>
        </B>
        <B>
          <loc>
            <x>700</x>
            <y>225</y>
          </loc>
          <B_texture>rightgate</B_texture>
        </B>
        <B>
          <loc>
            <x>350</x>
            <y>450</y>
          </loc>
          <B_texture>bottomgate</B_texture>
        </B>
        <B>
          <loc>
            <x>450</x>
            <y>100</y>
          </loc>
          <B_texture>block15</B_texture>
        </B>
        <B>
          <loc>
            <x>550</x>
            <y>150</y>
          </loc>
          <B_texture>block13</B_texture>
        </B>
        <B>
          <loc>
            <x>600</x>
            <y>200</y>
          </loc>
          <B_texture>block12</B_texture>
        </B>
        <B>
          <loc>
            <x>600</x>
            <y>300</y>
          </loc>
          <B_texture>block12</B_texture>
        </B>
        <B>
          <loc>
            <x>550</x>
            <y>350</y>
          </loc>
          <B_texture>block13</B_texture>
        </B>
        <B>
          <loc>
            <x>450</x>
            <y>400</y>
          </loc>
          <B_texture>block15</B_texture>
        </B>
      </blocks>
      <items num="0" />
      <enemies num="0" />
    </type>
  </room4>
  <room5>
    <type>
      <blocks num="18">
        <B>
          <loc>
            <x>100</x>
            <y>100</y>
          </loc>
          <B_texture>floor</B_texture>
        </B>
        <B>
          <loc>
            <x>0</x>
            <y>0</y>
          </loc>
          <B_texture>leftwall</B_texture>
        </B>
        <B>
          <loc>
            <x>100</x>
            <y>0</y>
          </loc>
          <B_texture>topwall</B_texture>
        </B>
        <B>
          <loc>
            <x>700</x>
            <y>0</y>
          </loc>
          <B_texture>rightwall</B_texture>
        </B>
        <B>
          <loc>
            <x>100</x>
            <y>450</y>
          </loc>
          <B_texture>bottomwall</B_texture>
        </B>
        <B>
          <loc>
            <x>0</x>
            <y>225</y>
          </loc>
          <B_texture>leftgate</B_texture>
        </B>
        <B>
          <loc>
            <x>350</x>
            <y>0</y>
          </loc>
          <B_texture>topwall11</B_texture>
        </B>
        <B>
          <loc>
            <x>700</x>
            <y>225</y>
          </loc>
          <B_texture>rightwall11</B_texture>
        </B>
        <B>
          <loc>
            <x>350</x>
            <y>450</y>
          </loc>
          <B_texture>bottomwall11</B_texture>
        </B>
        <B>
          <loc>
            <x>150</x>
            <y>150</y>
          </loc>
          <B_texture>block110</B_texture>
        </B>
        <B>
          <loc>
            <x>150</x>
            <y>200</y>
          </loc>
          <B_texture>block41</B_texture>
        </B>
        <B>
          <loc>
            <x>200</x>
            <y>350</y>
          </loc>
          <B_texture>block13</B_texture>
        </B>
        <B>
          <loc>
            <x>600</x>
            <y>200</y>
          </loc>
          <B_texture>block41</B_texture>
        </B>
        <B>
          <loc>
            <x>450</x>
            <y>350</y>
          </loc>
          <B_texture>block13</B_texture>
        </B>
        <B>
          <loc>
            <x>300</x>
            <y>200</y>
          </loc>
          <B_texture>rightStatue</B_texture>
        </B>
        <B>
          <loc>
            <x>250</x>
            <y>250</y>
          </loc>
          <B_texture>rightStatue</B_texture>
        </B>
        <B>
          <loc>
            <x>450</x>
            <y>200</y>
          </loc>
          <B_texture>leftStatue</B_texture>
        </B>
        <B>
          <loc>
            <x>500</x>
            <y>250</y>
          </loc>
          <B_texture>leftStatue</B_texture>
        </B>
      </blocks>
      <items num="0" />
      <enemies num="0" />
    </type>
  </room5>
  <room6>
    <type>
      <blocks num="10">
        <B>
          <loc>
            <x>100</x>
            <y>100</y>
          </loc>
          <B_texture>floor</B_texture>
        </B>
        <B>
          <loc>
            <x>0</x>
            <y>0</y>
          </loc>
          <B_texture>leftwall</B_texture>
        </B>
        <B>
          <loc>
            <x>100</x>
            <y>0</y>
          </loc>
          <B_texture>topwall</B_texture>
        </B>
        <B>
          <loc>
            <x>700</x>
            <y>0</y>
          </loc>
          <B_texture>rightwall</B_texture>
        </B>
        <B>
          <loc>
            <x>100</x>
            <y>450</y>
          </loc>
          <B_texture>bottomwall</B_texture>
        </B>
        <B>
          <loc>
            <x>0</x>
            <y>225</y>
          </loc>
          <B_texture>leftgate</B_texture>
        </B>
        <B>
          <loc>
            <x>350</x>
            <y>0</y>
          </loc>
          <B_texture>topwall11</B_texture>
        </B>
        <B>
          <loc>
            <x>700</x>
            <y>225</y>
          </loc>
          <B_texture>rightgate</B_texture>
        </B>
        <B>
          <loc>
            <x>350</x>
            <y>450</y>
          </loc>
          <B_texture>bottomgate</B_texture>
        </B>
        <B>
          <loc>
            <x>350</x>
            <y>250</y>
          </loc>
          <B_texture>block</B_texture>
        </B>
      </blocks>
      <items num="0" />
      <enemies num="0" />
    </type>
  </room6>
  <room7>
    <type>
      <blocks num="14">
        <B>
          <loc>
            <x>100</x>
            <y>100</y>
          </loc>
          <B_texture>floor</B_texture>
        </B>
        <B>
          <loc>
            <x>0</x>
            <y>0</y>
          </loc>
          <B_texture>leftwall</B_texture>
        </B>
        <B>
          <loc>
            <x>100</x>
            <y>0</y>
          </loc>
          <B_texture>topwall</B_texture>
        </B>
        <B>
          <loc>
            <x>700</x>
            <y>0</y>
          </loc>
          <B_texture>rightwall</B_texture>
        </B>
        <B>
          <loc>
            <x>100</x>
            <y>450</y>
          </loc>
          <B_texture>bottomwall</B_texture>
        </B>
        <B>
          <loc>
            <x>0</x>
            <y>225</y>
          </loc>
          <B_texture>leftgate</B_texture>
        </B>
        <B>
          <loc>
            <x>350</x>
            <y>0</y>
          </loc>
          <B_texture>topgate</B_texture>
        </B>
        <B>
          <loc>
            <x>700</x>
            <y>225</y>
          </loc>
          <B_texture>rightgate</B_texture>
        </B>
        <B>
          <loc>
            <x>350</x>
            <y>450</y>
          </loc>
          <B_texture>bottomarch</B_texture>
        </B>
        <B>
          <loc>
            <x>150</x>
            <y>150</y>
          </loc>
          <B_texture>block12</B_texture>
        </B>
        <B>
          <loc>
            <x>150</x>
            <y>350</y>
          </loc>
          <B_texture>block12</B_texture>
        </B>
        <B>
          <loc>
            <x>350</x>
            <y>250</y>
          </loc>
          <B_texture>block12</B_texture>
        </B>
        <B>
          <loc>
            <x>550</x>
            <y>150</y>
          </loc>
          <B_texture>block12</B_texture>
        </B>
        <B>
          <loc>
            <x>550</x>
            <y>350</y>
          </loc>
          <B_texture>block12</B_texture>
        </B>
      </blocks>
      <items num="0" />
      <enemies num="0" />
    </type>
  </room7>
  <room8>
    <type>
      <blocks num="13">
        <B>
          <loc>
            <x>100</x>
            <y>100</y>
          </loc>
          <B_texture>floor</B_texture>
        </B>
        <B>
          <loc>
            <x>0</x>
            <y>0</y>
          </loc>
          <B_texture>leftwall</B_texture>
        </B>
        <B>
          <loc>
            <x>100</x>
            <y>0</y>
          </loc>
          <B_texture>topwall</B_texture>
        </B>
        <B>
          <loc>
            <x>700</x>
            <y>0</y>
          </loc>
          <B_texture>rightwall</B_texture>
        </B>
        <B>
          <loc>
            <x>100</x>
            <y>450</y>
          </loc>
          <B_texture>bottomwall</B_texture>
        </B>
        <B>
          <loc>
            <x>0</x>
            <y>225</y>
          </loc>
          <B_texture>leftgate</B_texture>
        </B>
        <B>
          <loc>
            <x>350</x>
            <y>0</y>
          </loc>
          <B_texture>topwall11</B_texture>
        </B>
        <B>
          <loc>
            <x>700</x>
            <y>225</y>
          </loc>
          <B_texture>rightgate</B_texture>
        </B>
        <B>
          <loc>
            <x>350</x>
            <y>450</y>
          </loc>
          <B_texture>bottomarch</B_texture>
        </B>
        <B>
          <loc>
            <x>200</x>
            <y>200</y>
          </loc>
          <B_texture>block</B_texture>
        </B>
        <B>
          <loc>
            <x>200</x>
            <y>300</y>
          </loc>
          <B_texture>block</B_texture>
        </B>
        <B>
          <loc>
            <x>550</x>
            <y>200</y>
          </loc>
          <B_texture>block</B_texture>
        </B>
        <B>
          <loc>
            <x>550</x>
            <y>300</y>
          </loc>
          <B_texture>block</B_texture>
        </B>
      </blocks>
      <items num="0" />
      <enemies num="0" />
    </type>
  </room8>
  <room9>
    <type>
      <blocks num="24">
        <B>
          <loc>
            <x>100</x>
            <y>100</y>
          </loc>
          <B_texture>floor</B_texture>
        </B>
        <B>
          <loc>
            <x>0</x>
            <y>0</y>
          </loc>
          <B_texture>leftwall</B_texture>
        </B>
        <B>
          <loc>
            <x>100</x>
            <y>0</y>
          </loc>
          <B_texture>topwall</B_texture>
        </B>
        <B>
          <loc>
            <x>700</x>
            <y>0</y>
          </loc>
          <B_texture>rightwall</B_texture>
        </B>
        <B>
          <loc>
            <x>100</x>
            <y>450</y>
          </loc>
          <B_texture>bottomwall</B_texture>
        </B>
        <B>
          <loc>
            <x>0</x>
            <y>225</y>
          </loc>
          <B_texture>leftgate</B_texture>
        </B>
        <B>
          <loc>
            <x>350</x>
            <y>0</y>
          </loc>
          <B_texture>topgate</B_texture>
        </B>
        <B>
          <loc>
            <x>700</x>
            <y>225</y>
          </loc>
          <B_texture>rightwall11</B_texture>
        </B>
        <B>
          <loc>
            <x>350</x>
            <y>450</y>
          </loc>
          <B_texture>bottomwall11</B_texture>
        </B>
        <B>
          <loc>
            <x>150</x>
            <y>150</y>
          </loc>
          <B_texture>block</B_texture>
        </B>
        <B>
          <loc>
            <x>250</x>
            <y>150</y>
          </loc>
          <B_texture>block</B_texture>
        </B>
        <B>
          <loc>
            <x>350</x>
            <y>150</y>
          </loc>
          <B_texture>block12</B_texture>
        </B>
        <B>
          <loc>
            <x>500</x>
            <y>150</y>
          </loc>
          <B_texture>block</B_texture>
        </B>
        <B>
          <loc>
            <x>600</x>
            <y>150</y>
          </loc>
          <B_texture>block</B_texture>
        </B>
        <B>
          <loc>
            <x>150</x>
            <y>250</y>
          </loc>
          <B_texture>block</B_texture>
        </B>
        <B>
          <loc>
            <x>250</x>
            <y>250</y>
          </loc>
          <B_texture>block</B_texture>
        </B>
        <B>
          <loc>
            <x>350</x>
            <y>250</y>
          </loc>
          <B_texture>block12</B_texture>
        </B>
        <B>
          <loc>
            <x>500</x>
            <y>250</y>
          </loc>
          <B_texture>block</B_texture>
        </B>
        <B>
          <loc>
            <x>600</x>
            <y>250</y>
          </loc>
          <B_texture>block</B_texture>
        </B>
        <B>
          <loc>
            <x>150</x>
            <y>350</y>
          </loc>
          <B_texture>block</B_texture>
        </B>
        <B>
          <loc>
            <x>250</x>
            <y>350</y>
          </loc>
          <B_texture>block</B_texture>
        </B>
        <B>
          <loc>
            <x>350</x>
            <y>350</y>
          </loc>
          <B_texture>block12</B_texture>
        </B>
        <B>
          <loc>
            <x>500</x>
            <y>350</y>
          </loc>
          <B_texture>block</B_texture>
        </B>
        <B>
          <loc>
            <x>600</x>
            <y>350</y>
          </loc>
          <B_texture>block</B_texture>
        </B>
      </blocks>
      <items num="0" />
      <enemies num="0" />
    </type>
  </room9>
  <room10>
    <type>
      <blocks num="10">
        <B>
          <loc>
            <x>100</x>
            <y>100</y>
          </loc>
          <B_texture>floor</B_texture>
        </B>
        <B>
          <loc>
            <x>0</x>
            <y>0</y>
          </loc>
          <B_texture>leftwall</B_texture>
        </B>
        <B>
          <loc>
            <x>100</x>
            <y>0</y>
          </loc>
          <B_texture>topwall</B_texture>
        </B>
        <B>
          <loc>
            <x>700</x>
            <y>0</y>
          </loc>
          <B_texture>rightwall</B_texture>
        </B>
        <B>
          <loc>
            <x>100</x>
            <y>450</y>
          </loc>
          <B_texture>bottomwall</B_texture>
        </B>
        <B>
          <loc>
            <x>0</x>
            <y>225</y>
          </loc>
          <B_texture>leftwall11</B_texture>
        </B>
        <B>
          <loc>
            <x>350</x>
            <y>0</y>
          </loc>
          <B_texture>topgate</B_texture>
        </B>
        <B>
          <loc>
            <x>700</x>
            <y>225</y>
          </loc>
          <B_texture>rightgate</B_texture>
        </B>
        <B>
          <loc>
            <x>350</x>
            <y>450</y>
          </loc>
          <B_texture>bottomwall11</B_texture>
        </B>
        <B>
          <loc>
            <x>350</x>
            <y>200</y>
          </loc>
          <B_texture>block32</B_texture>
        </B>
      </blocks>
      <items num="0" />
      <enemies num="0" />
    </type>
  </room10>
  <room11>
    <type>
      <blocks num="13">
        <B>
          <loc>
            <x>100</x>
            <y>100</y>
          </loc>
          <B_texture>floor</B_texture>
        </B>
        <B>
          <loc>
            <x>0</x>
            <y>0</y>
          </loc>
          <B_texture>leftwall</B_texture>
        </B>
        <B>
          <loc>
            <x>100</x>
            <y>0</y>
          </loc>
          <B_texture>topwall</B_texture>
        </B>
        <B>
          <loc>
            <x>700</x>
            <y>0</y>
          </loc>
          <B_texture>rightwall</B_texture>
        </B>
        <B>
          <loc>
            <x>100</x>
            <y>450</y>
          </loc>
          <B_texture>bottomwall</B_texture>
        </B>
        <B>
          <loc>
            <x>0</x>
            <y>225</y>
          </loc>
          <B_texture>leftgate</B_texture>
        </B>
        <B>
          <loc>
            <x>350</x>
            <y>0</y>
          </loc>
          <B_texture>toparch</B_texture>
        </B>
        <B>
          <loc>
            <x>700</x>
            <y>225</y>
          </loc>
          <B_texture>rightgate</B_texture>
        </B>
        <B>
          <loc>
            <x>350</x>
            <y>450</y>
          </loc>
          <B_texture>bottomgate</B_texture>
        </B>
        <B>
          <loc>
            <x>200</x>
            <y>200</y>
          </loc>
          <B_texture>block</B_texture>
        </B>
        <B>
          <loc>
            <x>550</x>
            <y>200</y>
          </loc>
          <B_texture>block</B_texture>
        </B>
        <B>
          <loc>
            <x>200</x>
            <y>300</y>
          </loc>
          <B_texture>block</B_texture>
        </B>
        <B>
          <loc>
            <x>550</x>
            <y>300</y>
          </loc>
          <B_texture>block</B_texture>
        </B>
      </blocks>
      <items num="0" />
      <enemies num="0" />
    </type>
  </room11>
  <room12>
    <type>
      <blocks num="13">
        <B>
          <loc>
            <x>100</x>
            <y>100</y>
          </loc>
          <B_texture>floor</B_texture>
        </B>
        <B>
          <loc>
            <x>0</x>
            <y>0</y>
          </loc>
          <B_texture>leftwall</B_texture>
        </B>
        <B>
          <loc>
            <x>100</x>
            <y>0</y>
          </loc>
          <B_texture>topwall</B_texture>
        </B>
        <B>
          <loc>
            <x>700</x>
            <y>0</y>
          </loc>
          <B_texture>rightwall</B_texture>
        </B>
        <B>
          <loc>
            <x>100</x>
            <y>450</y>
          </loc>
          <B_texture>bottomwall</B_texture>
        </B>
        <B>
          <loc>
            <x>0</x>
            <y>225</y>
          </loc>
          <B_texture>leftgate</B_texture>
        </B>
        <B>
          <loc>
            <x>350</x>
            <y>0</y>
          </loc>
          <B_texture>toparch</B_texture>
        </B>
        <B>
          <loc>
            <x>700</x>
            <y>225</y>
          </loc>
          <B_texture>rightwall11</B_texture>
        </B>
        <B>
          <loc>
            <x>350</x>
            <y>450</y>
          </loc>
          <B_texture>bottomwall11</B_texture>
        </B>
        <B>
          <loc>
            <x>200</x>
            <y>150</y>
          </loc>
          <B_texture>block</B_texture>
        </B>
        <B>
          <loc>
            <x>550</x>
            <y>150</y>
          </loc>
          <B_texture>block</B_texture>
        </B>
        <B>
          <loc>
            <x>200</x>
            <y>350</y>
          </loc>
          <B_texture>block</B_texture>
        </B>
        <B>
          <loc>
            <x>550</x>
            <y>350</y>
          </loc>
          <B_texture>block</B_texture>
        </B>
      </blocks>
      <items num="0" />
      <enemies num="0" />
    </type>
  </room12>
  <room13>
    <type>
      <blocks num="10">
        <B>
          <loc>
            <x>100</x>
            <y>100</y>
          </loc>
          <B_texture>floor</B_texture>
        </B>
        <B>
          <loc>
            <x>0</x>
            <y>0</y>
          </loc>
          <B_texture>leftwall</B_texture>
        </B>
        <B>
          <loc>
            <x>100</x>
            <y>0</y>
          </loc>
          <B_texture>topwall</B_texture>
        </B>
        <B>
          <loc>
            <x>700</x>
            <y>0</y>
          </loc>
          <B_texture>rightwall</B_texture>
        </B>
        <B>
          <loc>
            <x>100</x>
            <y>450</y>
          </loc>
          <B_texture>bottomwall</B_texture>
        </B>
        <B>
          <loc>
            <x>0</x>
            <y>225</y>
          </loc>
          <B_texture>leftwall11</B_texture>
        </B>
        <B>
          <loc>
            <x>350</x>
            <y>0</y>
          </loc>
          <B_texture>topgate</B_texture>
        </B>
        <B>
          <loc>
            <x>700</x>
            <y>225</y>
          </loc>
          <B_texture>rightwall11</B_texture>
        </B>
        <B>
          <loc>
            <x>350</x>
            <y>450</y>
          </loc>
          <B_texture>bottomgate</B_texture>
        </B>
        <B>
          <loc>
            <x>350</x>
            <y>200</y>
          </loc>
          <B_texture>block32</B_texture>
        </B>
      </blocks>
      <items num="0" />
      <enemies num="0" />
    </type>
  </room13>
  <room14>
    <type>
      <blocks num="9">
        <B>
          <loc>
            <x>100</x>
            <y>100</y>
          </loc>
          <B_texture>floor</B_texture>
        </B>
        <B>
          <loc>
            <x>0</x>
            <y>0</y>
          </loc>
          <B_texture>leftwall</B_texture>
        </B>
        <B>
          <loc>
            <x>100</x>
            <y>0</y>
          </loc>
          <B_texture>topwall</B_texture>
        </B>
        <B>
          <loc>
            <x>700</x>
            <y>0</y>
          </loc>
          <B_texture>rightwall</B_texture>
        </B>
        <B>
          <loc>
            <x>100</x>
            <y>450</y>
          </loc>
          <B_texture>bottomwall</B_texture>
        </B>
        <B>
          <loc>
            <x>0</x>
            <y>225</y>
          </loc>
          <B_texture>leftwall11</B_texture>
        </B>
        <B>
          <loc>
            <x>350</x>
            <y>0</y>
          </loc>
          <B_texture>topwall11</B_texture>
        </B>
        <B>
          <loc>
            <x>700</x>
            <y>225</y>
          </loc>
          <B_texture>rightgate</B_texture>
        </B>
        <B>
          <loc>
            <x>350</x>
            <y>450</y>
          </loc>
          <B_texture>bottomwall11</B_texture>
        </B>
      </blocks>
		<items num="1">
			<I>
				<loc>
					<x>100</x>
					<y>400</y>
				</loc>
				<I_texture>key</I_texture>
			</I>
		</items>
		<enemies num="3">
			<E move="true">
				<loc>
					<x>150</x>
					<y>150</y>
				</loc>
				<dir>0</dir>
				<E_texture>
					<up>blueBat</up>
					<down>blueBat</down>
					<right>blueBat</right>
					<left>blueBat</left>
				</E_texture>
				<projectile fire="false"/>
				<routes>
					<R>
						<loc>
							<x>650</x>
							<y>150</y>
						</loc>
						<dir>1</dir>
					</R>
				</routes>
				<timer/>
			</E>
			<E move="true">
				<loc>
					<x>250</x>
					<y>200</y>
				</loc>
				<dir>3</dir>
				<E_texture>
					<up>blueBat</up>
					<down>blueBat</down>
					<right>blueBat</right>
					<left>blueBat</left>
				</E_texture>
				<projectile fire="false"/>
				<routes>
					<R>
						<loc>
							<x>250</x>
							<y>300</y>
						</loc>
						<dir>0</dir>
					</R>
					<R>
						<loc>
							<x>650</x>
							<y>300</y>
						</loc>
						<dir>2</dir>
					</R>
					<R>
						<loc>
							<x>650</x>
							<y>200</y>
						</loc>
						<dir>1</dir>
					</R>
				</routes>
				<timer/>
			</E>
			<E move="true">
				<loc>
					<x>150</x>
					<y>350</y>
				</loc>
				<dir>0</dir>
				<E_texture>
					<up>blueBat</up>
					<down>blueBat</down>
					<right>blueBat</right>
					<left>blueBat</left>
				</E_texture>
				<projectile fire="false"/>
				<routes>
					<R>
						<loc>
							<x>650</x>
							<y>350</y>
						</loc>
						<dir>
							1
						</dir>
					</R>
				</routes>
				<timer/>
			</E>
		</enemies>
    </type>
  </room14>
  <room15>
    <type>
      <blocks num="26">
        <B>
          <loc>
            <x>100</x>
            <y>100</y>
          </loc>
          <B_texture>floor</B_texture>
        </B>
        <B>
          <loc>
            <x>0</x>
            <y>0</y>
          </loc>
          <B_texture>leftwall</B_texture>
        </B>
        <B>
          <loc>
            <x>100</x>
            <y>0</y>
          </loc>
          <B_texture>topwall</B_texture>
        </B>
        <B>
          <loc>
            <x>700</x>
            <y>0</y>
          </loc>
          <B_texture>rightwall</B_texture>
        </B>
        <B>
          <loc>
            <x>100</x>
            <y>450</y>
          </loc>
          <B_texture>bottomwall</B_texture>
        </B>
        <B>
          <loc>
            <x>0</x>
            <y>225</y>
          </loc>
          <B_texture>leftgate</B_texture>
        </B>
        <B>
          <loc>
            <x>350</x>
            <y>0</y>
          </loc>
          <B_texture>topgate</B_texture>
        </B>
        <B>
          <loc>
            <x>700</x>
            <y>225</y>
          </loc>
          <B_texture>rightgate</B_texture>
        </B>
        <B>
          <loc>
            <x>350</x>
            <y>450</y>
          </loc>
          <B_texture>bottomgate</B_texture>
        </B>
        <B>
          <loc>
            <x>150</x>
            <y>150</y>
          </loc>
          <B_texture>rightStatue</B_texture>
        </B>
        <B>
          <loc>
            <x>300</x>
            <y>150</y>
          </loc>
          <B_texture>rightStatue</B_texture>
        </B>
        <B>
          <loc>
            <x>450</x>
            <y>150</y>
          </loc>
          <B_texture>leftStatue</B_texture>
        </B>
        <B>
          <loc>
            <x>600</x>
            <y>150</y>
          </loc>
          <B_texture>leftStatue</B_texture>
        </B>
        <B>
          <loc>
            <x>150</x>
            <y>250</y>
          </loc>
          <B_texture>rightStatue</B_texture>
        </B>
        <B>
          <loc>
            <x>300</x>
            <y>250</y>
          </loc>
          <B_texture>rightStatue</B_texture>
        </B>
        <B>
          <loc>
            <x>450</x>
            <y>250</y>
          </loc>
          <B_texture>leftStatue</B_texture>
        </B>
        <B>
          <loc>
            <x>600</x>
            <y>250</y>
          </loc>
          <B_texture>leftStatue</B_texture>
        </B>
        <B>
          <loc>
            <x>150</x>
            <y>350</y>
          </loc>
          <B_texture>rightStatue</B_texture>
        </B>
        <B>
          <loc>
            <x>300</x>
            <y>350</y>
          </loc>
          <B_texture>rightStatue</B_texture>
        </B>
        <B>
          <loc>
            <x>450</x>
            <y>350</y>
          </loc>
          <B_texture>leftStatue</B_texture>
        </B>
        <B>
          <loc>
            <x>600</x>
            <y>350</y>
          </loc>
          <B_texture>leftStatue</B_texture>
        </B>
        <B>
          <loc>
            <x>250</x>
            <y>350</y>
          </loc>
          <B_texture>blueSand</B_texture>
        </B>
        <B>
          <loc>
            <x>250</x>
            <y>400</y>
          </loc>
          <B_texture>blueSand12</B_texture>
        </B>
        <B>
          <loc>
            <x>350</x>
            <y>300</y>
          </loc>
          <B_texture>blueSand32</B_texture>
        </B>
        <B>
          <loc>
            <x>450</x>
            <y>400</y>
          </loc>
          <B_texture>blueSand12</B_texture>
        </B>
        <B>
          <loc>
            <x>500</x>
            <y>350</y>
          </loc>
          <B_texture>blueSand</B_texture>
        </B>
      </blocks>
		<items num="0" />
		<enemies num="0" />
    </type>
  </room15>
  <room16>
    <type>
      <blocks num="11">
        <B>
          <loc>
            <x>100</x>
            <y>100</y>
          </loc>
          <B_texture>floor</B_texture>
        </B>
        <B>
          <loc>
            <x>0</x>
            <y>0</y>
          </loc>
          <B_texture>leftwall</B_texture>
        </B>
        <B>
          <loc>
            <x>100</x>
            <y>0</y>
          </loc>
          <B_texture>topwall</B_texture>
        </B>
        <B>
          <loc>
            <x>700</x>
            <y>0</y>
          </loc>
          <B_texture>rightwall</B_texture>
        </B>
        <B>
          <loc>
            <x>100</x>
            <y>450</y>
          </loc>
          <B_texture>bottomwall</B_texture>
        </B>
        <B>
          <loc>
            <x>0</x>
            <y>225</y>
          </loc>
          <B_texture>leftgate</B_texture>
        </B>
        <B>
          <loc>
            <x>350</x>
            <y>0</y>
          </loc>
          <B_texture>topwall11</B_texture>
        </B>
        <B>
          <loc>
            <x>700</x>
            <y>225</y>
          </loc>
          <B_texture>rightwall11</B_texture>
        </B>
        <B>
          <loc>
            <x>350</x>
            <y>450</y>
          </loc>
          <B_texture>bottomwall11</B_texture>
        </B>
        <B>
          <loc>
            <x>200</x>
            <y>200</y>
          </loc>
          <B_texture>block32</B_texture>
        </B>
        <B>
          <loc>
            <x>500</x>
            <y>200</y>
          </loc>
          <B_texture>block32</B_texture>
        </B>
      </blocks>
		<items num="1">
			<I>
				<loc>
					<x>375</x>
					<y>275</y>
				</loc>
				<I_texture>key</I_texture>
			</I>
		</items>
		<enemies num="5">
			<E move="true">
				<loc>
					<x>625</x>
					<y>130</y>
				</loc>
				<dir>1</dir>
				<E_texture>
					<up>stalfos</up>
					<down>stalfos</down>
					<right>stalfos</right>
					<left>stalfos</left>
				</E_texture>
				<projectile fire="false"/>
				<routes>
					<R>
						<loc>
							<x>325</x>
							<y>130</y>
						</loc>
						<dir>3</dir>
					</R>
					<R>
						<loc>
							<x>325</x>
							<y>320</y>
						</loc>
						<dir>0</dir>
					</R>
					<R>
						<loc>
							<x>625</x>
							<y>320</y>
						</loc>
						<dir>2</dir>
					</R>
				</routes>
				<timer/>
			</E>
			<E move="true">
				<loc>
					<x>625</x>
					<y>330</y>
				</loc>
				<dir>2</dir>
				<E_texture>
					<up>stalfos</up>
					<down>stalfos</down>
					<right>stalfos</right>
					<left>stalfos</left>
				</E_texture>
				<projectile fire="false"/>
				<routes>
					<R>
						<loc>
							<x>625</x>
							<y>80</y>
						</loc>
						<dir>1</dir>
					</R>
					<R>
						<loc>
							<x>80</x>
							<y>80</y>
						</loc>
						<dir>3</dir>
					</R>
					<R>
						<loc>
							<x>80</x>
							<y>330</y>
						</loc>
						<dir>0</dir>
					</R>
				</routes>
				<timer/>
			</E>
			<E move="true">
				<loc>
					<x>250</x>
					<y>350</y>
				</loc>
				<dir>0</dir>
				<E_texture>
					<up>stalfos</up>
					<down>stalfos</down>
					<right>stalfos</right>
					<left>stalfos</left>
				</E_texture>
				<projectile fire="false"/>
				<routes>
					<R>
						<loc>
							<x>625</x>
							<y>350</y>
						</loc>
						<dir>1</dir>
					</R>
					<R>
						<loc>
							<x>250</x>
							<y>350</y>
						</loc>
						<dir>3</dir>
					</R>
					<R>
						<loc>
							<x>250</x>
							<y>380</y>
						</loc>
						<dir>1</dir>
					</R>
					<R>
						<loc>
							<x>80</x>
							<y>380</y>
						</loc>
						<dir>2</dir>
					</R>
					<R>
						<loc>
							<x>80</x>
							<y>350</y>
						</loc>
						<dir>0</dir>
					</R>
				</routes>
				<timer/>
			</E>
			<E move="true">
				<loc>
					<x>400</x>
					<y>150</y>
				</loc>
				<dir>3</dir>
				<E_texture>
					<up>stalfos</up>
					<down>stalfos</down>
					<right>stalfos</right>
					<left>stalfos</left>
				</E_texture>
				<projectile fire="false"/>
				<routes>
					<R>
						<loc>
							<x>400</x>
							<y>380</y>
						</loc>
						<dir>2</dir>
					</R>
				</routes>
				<timer/>
			</E>
			<E move="true">
				<loc>
					<x>425</x>
					<y>280</y>
				</loc>
				<dir>1</dir>
				<E_texture>
					<up>stalfos</up>
					<down>stalfos</down>
					<right>stalfos</right>
					<left>stalfos</left>
				</E_texture>
				<projectile fire="false"/>
				<routes>
					<R>
						<loc>
							<x>290</x>
							<y>280</y>
						</loc>
						<dir>0</dir>
					</R>
				</routes>
				<timer/>
			</E>
		</enemies>
    </type>
  </room16>
</Level1>